muicebot-1.1.4.post1.dist-info/METADATA
muicebot-1.1.4.post1.dist-info/WHEEL
muicebot-1.1.4.post1.dist-info/entry_points.txt
muicebot-1.1.4.post1.dist-info/licenses/LICENSE
muicebot/__init__.py
muicebot/builtin_plugins/access_control.py
muicebot/builtin_plugins/get_current_time.py
muicebot/builtin_plugins/get_username.py
muicebot/builtin_plugins/migrations.py
muicebot/builtin_plugins/moe_chat.py
muicebot/builtin_plugins/plugin_store/__init__.py
muicebot/builtin_plugins/plugin_store/config.py
muicebot/builtin_plugins/plugin_store/models.py
muicebot/builtin_plugins/plugin_store/register.py
muicebot/builtin_plugins/plugin_store/store.py
muicebot/builtin_plugins/thought_processor.py
muicebot/builtin_templates/Muice.jinja2
muicebot/builtin_templates/Muika.jinja2
muicebot/config.py
muicebot/database/__init__.py
muicebot/database/crud.py
muicebot/database/orm_models.py
muicebot/llm/__init__.py
muicebot/llm/_base.py
muicebot/llm/_config.py
muicebot/llm/_dependencies.py
muicebot/llm/_schema.py
muicebot/llm/_wrapper.py
muicebot/llm/embeddings/__init__.py
muicebot/llm/embeddings/azure.py
muicebot/llm/embeddings/dashscope.py
muicebot/llm/embeddings/gemini.py
muicebot/llm/embeddings/ollama.py
muicebot/llm/embeddings/openai.py
muicebot/llm/loader.py
muicebot/llm/providers/__init__.py
muicebot/llm/providers/_echo.py
muicebot/llm/providers/azure.py
muicebot/llm/providers/dashscope.py
muicebot/llm/providers/gemini.py
muicebot/llm/providers/ollama.py
muicebot/llm/providers/openai.py
muicebot/llm/registry.py
muicebot/llm/utils/images.py
muicebot/llm/utils/tools.py
muicebot/migrations/8141d1806585_first_revision.py
muicebot/migrations/9dd95c5e9b4d_add_user_table.py
muicebot/migrations/f55e998a17fa_add_usage_table.py
muicebot/models.py
muicebot/muice.py
muicebot/onebot.py
muicebot/plugin/__init__.py
muicebot/plugin/context.py
muicebot/plugin/func_call/__init__.py
muicebot/plugin/func_call/_types.py
muicebot/plugin/func_call/caller.py
muicebot/plugin/func_call/parameter.py
muicebot/plugin/func_call/utils.py
muicebot/plugin/hook/__init__.py
muicebot/plugin/hook/_types.py
muicebot/plugin/hook/manager.py
muicebot/plugin/loader.py
muicebot-1.1.4.post1.dist-info/RECORD
