Metadata-Version: 2.1
Name: MuiceBot
Version: 1.1.4.post1
Summary: Muice-Chatbot 的 NoneBot2 实现
Author-Email: Moemu <i@snowy.moe>
Requires-Python: <3.14,>=3.10.0
Requires-Dist: aiosqlite>=0.17.0
Requires-Dist: APScheduler>=3.11.0
Requires-Dist: fleep>=1.0.1
Requires-Dist: jinja2>=3.1.6
Requires-Dist: nonebot2>=2.4.1
Requires-Dist: nonebot-adapter-onebot>=2.4.6
Requires-Dist: nonebot_plugin_alconna>=0.57.6
Requires-Dist: nonebot_plugin_apscheduler>=0.5.0
Requires-Dist: nonebot_plugin_localstore>=0.7.3
Requires-Dist: nonebot-plugin-orm>=0.7.7
Requires-Dist: nonebot_plugin_session>=0.3.2
Requires-Dist: nonebot_plugin_userinfo>=0.2.6
Requires-Dist: numpy>=1.26.4
Requires-Dist: openai>=1.64.0
Requires-Dist: pydantic>=2.10.5
Requires-Dist: pyyaml>=6.0.2
Requires-Dist: httpx>=0.27.0
Requires-Dist: ruamel.yaml>=0.18.10
Requires-Dist: SQLAlchemy>=2.0.38
Requires-Dist: toml>=0.10.2; python_version < "3.11"
Requires-Dist: websocket_client>=1.8.0
Requires-Dist: watchdog>=6.0.0
Requires-Dist: mcp[cli]>=1.9.0
Requires-Dist: aiohttp>=3.12.13
Provides-Extra: standard
Requires-Dist: azure-ai-inference>=1.0.0b7; extra == "standard"
Requires-Dist: dashscope>=1.22.1; extra == "standard"
Requires-Dist: google-genai>=1.8.0; extra == "standard"
Requires-Dist: ollama>=0.4.7; extra == "standard"
Requires-Dist: soundfile>=0.13.1; extra == "standard"
Requires-Dist: pytz>=2025.2; extra == "standard"
Provides-Extra: dev
Requires-Dist: pre-commit>=4.1.0; extra == "dev"
Requires-Dist: mypy>=1.15.0; extra == "dev"
Requires-Dist: black>=25.1.0; extra == "dev"
Requires-Dist: types-PyYAML; extra == "dev"
